{"files":[{"culture":"","installRoot":"","ngen":null,"path":"C:\\Users\\toaurs-he\\source\\repos\\UniqueEnumValueFixer\\UniqueEnumValueFixer\\bin\\Debug\\netstandard1.3\\UniqueEnumValueFixer.dll","targetPath":"","vsixSubPath":""},{"culture":"","installRoot":"","ngen":null,"path":"C:\\Users\\toaurs-he\\source\\repos\\UniqueEnumValueFixer\\UniqueEnumValueFixer.Vsix\\binoculars.PNG","targetPath":"","vsixSubPath":""},{"culture":"","installRoot":"","ngen":null,"path":"C:\\Users\\toaurs-he\\source\\repos\\UniqueEnumValueFixer\\UniqueEnumValueFixer\\tools\\install.ps1","targetPath":"tools\\install.ps1","vsixSubPath":""},{"culture":"","installRoot":"","ngen":null,"path":"C:\\Users\\toaurs-he\\source\\repos\\UniqueEnumValueFixer\\UniqueEnumValueFixer\\tools\\uninstall.ps1","targetPath":"tools\\uninstall.ps1","vsixSubPath":""}]}